[
  {
    "generated_hit_rate": 0.15625,
    "relaxed_hit_rate": 0.125,
    "stable_fraction": 0.5625,
    "stable_generated_in_window": 0.09375,
    "stable_relaxed_in_window": 0.0625,
    "avg_energy_above_hull_per_atom": 0.14454541059407888,
    "name": "scale32_v2_baseline",
    "gamma": 1.0,
    "seed": 2026,
    "self_correct": false,
    "num_samples": 32
  },
  {
    "generated_hit_rate": 0.375,
    "relaxed_hit_rate": 0.3125,
    "stable_fraction": 0.4375,
    "stable_generated_in_window": 0.15625,
    "stable_relaxed_in_window": 0.15625,
    "avg_energy_above_hull_per_atom": 0.1495584753613372,
    "name": "scale32_v2_self_correct",
    "gamma": 1.0,
    "seed": 2026,
    "self_correct": true,
    "num_samples": 32
  },
  {
    "name": "frontier_g2.0_s2026_base",
    "gamma": 2.0,
    "seed": 2026,
    "self_correct": false,
    "num_samples": 32,
    "generated_hit_rate": 0.34375,
    "relaxed_hit_rate": 0.1875,
    "stable_fraction": 0.53125,
    "stable_generated_in_window": 0.125,
    "stable_relaxed_in_window": 0.09375,
    "avg_energy_above_hull_per_atom": 0.1466867766058581,
    "generation_time_s": 890.0447859764099
  },
  {
    "name": "frontier_g2.0_s2026_sc",
    "gamma": 2.0,
    "seed": 2026,
    "self_correct": true,
    "num_samples": 32,
    "generated_hit_rate": 0.3125,
    "relaxed_hit_rate": 0.3125,
    "stable_fraction": 0.6875,
    "stable_generated_in_window": 0.15625,
    "stable_relaxed_in_window": 0.15625,
    "avg_energy_above_hull_per_atom": 0.09451375837462044,
    "generation_time_s": 907.7608308792114
  },
  {
    "name": "frontier_g1.0_s42_base",
    "gamma": 1.0,
    "seed": 42,
    "self_correct": false,
    "num_samples": 32,
    "generated_hit_rate": 0.15625,
    "relaxed_hit_rate": 0.1875,
    "stable_fraction": 0.59375,
    "stable_generated_in_window": 0.15625,
    "stable_relaxed_in_window": 0.15625,
    "avg_energy_above_hull_per_atom": 0.11749776874995904,
    "generation_time_s": 442.0542905330658
  },
  {
    "name": "frontier_g1.0_s42_sc",
    "gamma": 1.0,
    "seed": 42,
    "self_correct": true,
    "num_samples": 32,
    "generated_hit_rate": 0.25,
    "relaxed_hit_rate": 0.28125,
    "stable_fraction": 0.34375,
    "stable_generated_in_window": 0.09375,
    "stable_relaxed_in_window": 0.125,
    "avg_energy_above_hull_per_atom": 0.15699865363275012,
    "generation_time_s": 469.1512541770935
  },
  {
    "name": "frontier_g1.0_s137_base",
    "gamma": 1.0,
    "seed": 137,
    "self_correct": false,
    "num_samples": 32,
    "generated_hit_rate": 0.1875,
    "relaxed_hit_rate": 0.25,
    "stable_fraction": 0.28125,
    "stable_generated_in_window": 0.03125,
    "stable_relaxed_in_window": 0.0625,
    "avg_energy_above_hull_per_atom": 0.17934559441831793,
    "generation_time_s": 546.9778251647949
  },
  {
    "name": "frontier_g1.0_s137_sc",
    "gamma": 1.0,
    "seed": 137,
    "self_correct": true,
    "num_samples": 32,
    "generated_hit_rate": 0.09375,
    "relaxed_hit_rate": 0.0625,
    "stable_fraction": 0.4375,
    "stable_generated_in_window": 0.0,
    "stable_relaxed_in_window": 0.0,
    "avg_energy_above_hull_per_atom": 0.13429380219897458,
    "generation_time_s": 568.7456223964691
  },
  {
    "name": "frontier_g0.5_s2026_base",
    "gamma": 0.5,
    "seed": 2026,
    "self_correct": false,
    "num_samples": 32,
    "generated_hit_rate": 0.0625,
    "relaxed_hit_rate": 0.0625,
    "stable_fraction": 0.5,
    "stable_generated_in_window": 0.0,
    "stable_relaxed_in_window": 0.0,
    "avg_energy_above_hull_per_atom": 0.12519567353704836,
    "generation_time_s": 871.0651621818542
  },
  {
    "name": "frontier_g0.5_s2026_sc",
    "gamma": 0.5,
    "seed": 2026,
    "self_correct": true,
    "num_samples": 32,
    "generated_hit_rate": 0.09375,
    "relaxed_hit_rate": 0.09375,
    "stable_fraction": 0.46875,
    "stable_generated_in_window": 0.0625,
    "stable_relaxed_in_window": 0.0625,
    "avg_energy_above_hull_per_atom": 0.11424656187828494,
    "generation_time_s": 895.1076431274414
  },
  {
    "name": "frontier_g1.5_s2026_base",
    "gamma": 1.5,
    "seed": 2026,
    "self_correct": false,
    "num_samples": 32,
    "generated_hit_rate": 0.15625,
    "relaxed_hit_rate": 0.1875,
    "stable_fraction": 0.5,
    "stable_generated_in_window": 0.09375,
    "stable_relaxed_in_window": 0.125,
    "avg_energy_above_hull_per_atom": 0.11695377716037475,
    "generation_time_s": 877.9000291824341
  },
  {
    "name": "frontier_g1.5_s2026_sc",
    "gamma": 1.5,
    "seed": 2026,
    "self_correct": true,
    "num_samples": 32,
    "generated_hit_rate": 0.40625,
    "relaxed_hit_rate": 0.4375,
    "stable_fraction": 0.46875,
    "stable_generated_in_window": 0.25,
    "stable_relaxed_in_window": 0.25,
    "avg_energy_above_hull_per_atom": 0.11534739322361001,
    "generation_time_s": 901.6071095466614
  },
  {
    "name": "frontier_g3.0_s2026_base",
    "gamma": 3.0,
    "seed": 2026,
    "self_correct": false,
    "num_samples": 32,
    "generated_hit_rate": 0.5,
    "relaxed_hit_rate": 0.4375,
    "stable_fraction": 0.46875,
    "stable_generated_in_window": 0.15625,
    "stable_relaxed_in_window": 0.125,
    "avg_energy_above_hull_per_atom": 0.19138678369271725,
    "generation_time_s": 888.7630863189697
  },
  {
    "name": "frontier_g3.0_s2026_sc",
    "gamma": 3.0,
    "seed": 2026,
    "self_correct": true,
    "num_samples": 32,
    "generated_hit_rate": 0.375,
    "relaxed_hit_rate": 0.375,
    "stable_fraction": 0.3125,
    "stable_generated_in_window": 0.125,
    "stable_relaxed_in_window": 0.125,
    "avg_energy_above_hull_per_atom": 0.1724716228336612,
    "generation_time_s": 901.9268262386322
  }
]